ablelabs/__init__.py
ablelabs/neon/__init__.py
ablelabs/neon/common/__init__.py
ablelabs/neon/common/path.py
ablelabs/neon/common/alma/__init__.py
ablelabs/neon/common/alma/constants.py
ablelabs/neon/common/alma/enums.py
ablelabs/neon/common/alma/structs.py
ablelabs/neon/common/notable/__init__.py
ablelabs/neon/common/notable/constants.py
ablelabs/neon/common/notable/enums.py
ablelabs/neon/common/notable/structs.py
ablelabs/neon/common/notable/kribb/__init__.py
ablelabs/neon/common/notable/kribb/structs.py
ablelabs/neon/common/notable/nanophilia/__init__.py
ablelabs/neon/common/notable/nanophilia/enums.py
ablelabs/neon/common/notable/nanophilia/structs.py
ablelabs/neon/common/suitable/__init__.py
ablelabs/neon/common/suitable/constants.py
ablelabs/neon/common/suitable/enums.py
ablelabs/neon/common/suitable/structs.py
ablelabs/neon/controllers/__init__.py
ablelabs/neon/controllers/alma/__init__.py
ablelabs/neon/controllers/alma/sample.py
ablelabs/neon/controllers/alma/api/__init__.py
ablelabs/neon/controllers/alma/api/axis_api.py
ablelabs/neon/controllers/alma/api/deck_module.py
ablelabs/neon/controllers/alma/api/get_api.py
ablelabs/neon/controllers/alma/api/robot_api.py
ablelabs/neon/controllers/alma/api/robot_router.py
ablelabs/neon/controllers/alma/api/set_api.py
ablelabs/neon/controllers/alma/api/time_api.py
ablelabs/neon/controllers/alma/api/upper_module.py
ablelabs/neon/controllers/alma/api/deck_modules/__init__.py
ablelabs/neon/controllers/alma/api/deck_modules/heater.py
ablelabs/neon/controllers/alma/api/deck_modules/inspector.py
ablelabs/neon/controllers/alma/api/time/__init__.py
ablelabs/neon/controllers/alma/api/time/upper_module.py
ablelabs/neon/controllers/alma/api/time/upper_modules/__init__.py
ablelabs/neon/controllers/alma/api/time/upper_modules/gripper.py
ablelabs/neon/controllers/alma/api/time/upper_modules/pipette.py
ablelabs/neon/controllers/alma/api/upper_modules/__init__.py
ablelabs/neon/controllers/alma/api/upper_modules/gripper.py
ablelabs-0.4.13.dist-info/METADATA
ablelabs-0.4.13.dist-info/WHEEL
ablelabs-0.4.13.dist-info/top_level.txt
ablelabs-0.4.13.dist-info/RECORD
