Metadata-Version: 2.1
Name: ablelabs
Version: 0.4.13
Summary: ABLE Labs API
Home-page: https://github.com/ABLE-Labs/ABLE-API
Author: sypark
Author-email: sy.park@ablelabsinc.com
License: UNKNOWN
Platform: UNKNOWN
Classifier: Programming Language :: Python :: 3.10
Requires-Python: >=3.10
Requires-Dist: et-xmlfile>=1.1.0
Requires-Dist: future>=1.0.0
Requires-Dist: iso8601>=2.1.0
Requires-Dist: loguru>=0.7.2
Requires-Dist: openpyxl>=3.1.5
Requires-Dist: pyserial>=3.5
Requires-Dist: PyYAML>=6.0.1
Requires-Dist: httpx>=0.28.1
